setup.py
gb_distributions_probab/Binomialdistribution.py
gb_distributions_probab/Gaussiandistribution.py
gb_distributions_probab/Generaldistribution.py
gb_distributions_probab/__init__.py
gb_distributions_probab.egg-info/PKG-INFO
gb_distributions_probab.egg-info/SOURCES.txt
gb_distributions_probab.egg-info/dependency_links.txt
gb_distributions_probab.egg-info/not-zip-safe
gb_distributions_probab.egg-info/top_level.txt